setup.py
ant2mvn/__init__.py
ant2mvn/command_line.py
ant2mvn/logger.py
ant2mvn/mvn.py
ant2mvn/utils.py
ant2mvn.egg-info/PKG-INFO
ant2mvn.egg-info/SOURCES.txt
ant2mvn.egg-info/dependency_links.txt
ant2mvn.egg-info/entry_points.txt
ant2mvn.egg-info/not-zip-safe
ant2mvn.egg-info/requires.txt
ant2mvn.egg-info/top_level.txt
test/__init__.py
test/unit/__init__.py
test/unit/test_utils.py