Metadata-Version: 1.1
Name: ant2mvn
Version: 1.0.0
Summary: Making move Ant to Maven be easier
Home-page: http://techoffee.me
Author: Mario
Author-email: hengliang.jia@gmail.com
License: MIT
Platform: UNKNOWN
Classifier: Development Status :: 5 - Production/Stable
Classifier: Environment :: Console
Classifier: Intended Audience :: Developers
Classifier: License :: OSI Approved :: MIT License
Classifier: Operating System :: OS Independent
Classifier: Programming Language :: Python
